{"nodes": [{"id": "d_ic1101_ic1101_apps_web_app_page_tsx", "label": "page.tsx", "file_type": "code", "source_file": "D:\\ic1101\\ic1101\\apps\\web\\app\\page.tsx", "source_location": "L1"}, {"id": "app_page_services", "label": "services", "file_type": "code", "source_file": "D:\\ic1101\\ic1101\\apps\\web\\app\\page.tsx", "source_location": "L3"}, {"id": "app_page_homepage", "label": "HomePage()", "file_type": "code", "source_file": "D:\\ic1101\\ic1101\\apps\\web\\app\\page.tsx", "source_location": "L10"}], "edges": [{"source": "d_ic1101_ic1101_apps_web_app_page_tsx", "target": "d_ic1101_ic1101_apps_web_components_service_status_tsx", "relation": "imports_from", "context": "import", "confidence": "EXTRACTED", "source_file": "D:\\ic1101\\ic1101\\apps\\web\\app\\page.tsx", "source_location": "L1", "weight": 1.0}, {"source": "d_ic1101_ic1101_apps_web_app_page_tsx", "target": "components_service_status_servicestatus", "relation": "imports", "context": "import", "confidence": "EXTRACTED", "source_file": "D:\\ic1101\\ic1101\\apps\\web\\app\\page.tsx", "source_location": "L1", "weight": 1.0}, {"source": "d_ic1101_ic1101_apps_web_app_page_tsx", "target": "app_page_services", "relation": "contains", "confidence": "EXTRACTED", "source_file": "D:\\ic1101\\ic1101\\apps\\web\\app\\page.tsx", "source_location": "L3", "weight": 1.0}, {"source": "d_ic1101_ic1101_apps_web_app_page_tsx", "target": "app_page_homepage", "relation": "contains", "confidence": "EXTRACTED", "source_file": "D:\\ic1101\\ic1101\\apps\\web\\app\\page.tsx", "source_location": "L10", "weight": 1.0}], "raw_calls": [{"caller_nid": "app_page_homepage", "callee": "map", "is_member_call": true, "source_file": "D:\\ic1101\\ic1101\\apps\\web\\app\\page.tsx", "source_location": "L18"}]}